setup.py
distributions/Binomialdistribution.py
distributions/Gaussiandistribution.py
distributions/Generaldistribution.py
distributions/__init__.py
nobi_distributions.egg-info/PKG-INFO
nobi_distributions.egg-info/SOURCES.txt
nobi_distributions.egg-info/dependency_links.txt
nobi_distributions.egg-info/not-zip-safe
nobi_distributions.egg-info/top_level.txt