Metadata-Version: 1.0
Name: nobi-distributions
Version: 0.1
Summary: Gaussian and Binomial distributions
Home-page: UNKNOWN
Author: Emanuel Dickson Wanyonyi
Author-email: wanyonyi.d.emanuel@gmail.com
License: MIT
Platform: UNKNOWN
